[
  {
    "name": "Cataclysm",
    "author": "GGB0Y",
    "id": "123456",
    "pass": "123456",
    "song": "654321",
    "difficulty": "Extreme Demon",
    "difficultyValue": 10,
    "thumbnail": "https://i.imgur.com/UcC75Q6.png"
  },
  {
    "name": "Nine Circles",
    "author": "Zobros",
    "id": "234567",
    "pass": "456789",
    "song": "123456",
    "difficulty": "Insane Demon",
    "difficultyValue": 9,
    "thumbnail": "https://i.imgur.com/UcC75Q6.png"
  },
  {
    "name": "Acropolis",
    "author": "Zobros",
    "id": "345678",
    "pass": "159753",
    "song": "654321",
    "difficulty": "Hard Demon",
    "difficultyValue": 7,
    "thumbnail": "https://i.imgur.com/UcC75Q6.png"
  },
  {
    "name": "Clubstep",
    "author": "RobTop",
    "id": "987654",
    "pass": "111111",
    "song": "876543",
    "difficulty": "Medium Demon",
    "difficultyValue": 5,
    "thumbnail": "https://i.imgur.com/UcC75Q6.png"
  },
  {
    "name": "The Nightmare",
    "author": "Jax",
    "id": "765432",
    "pass": "222222",
    "song": "765432",
    "difficulty": "Easy Demon",
    "difficultyValue": 2,
    "thumbnail": "https://i.imgur.com/UcC75Q6.png"
  }
]
